setup.cfg
setup.py
hbcvt/__init__.py
hbcvt/h2b.py
hbcvt.egg-info/PKG-INFO
hbcvt.egg-info/SOURCES.txt
hbcvt.egg-info/dependency_links.txt
hbcvt.egg-info/requires.txt
hbcvt.egg-info/top_level.txt