Metadata-Version: 1.1
Name: hbcvt
Version: 1.0.1
Summary: Hangul to 6-Dot Braille converter
Home-page: https://github.com/hyonzin/hangul-braille-converter
Author: hyonzin
Author-email: hyeonjin507@gmail.com
License: MIT
Keywords: hangul to braille converter for the blind
Platform: UNKNOWN
Classifier: Development Status :: 3 - Alpha
Classifier: Intended Audience :: Developers
Classifier: Topic :: Text Processing :: Linguistic
Classifier: License :: OSI Approved :: MIT License
Classifier: Programming Language :: Python :: 2
Classifier: Programming Language :: Python :: 2.7
Classifier: Programming Language :: Python :: 3
Classifier: Programming Language :: Python :: 3.3
Classifier: Programming Language :: Python :: 3.4
Classifier: Programming Language :: Python :: 3.5
